betainc/__init__.py
betainc/betainc.c
betainc/betainc.cpython-310-x86_64-linux-gnu.so
betainc/betainc.pyx
betainc-1.0.0.dist-info/METADATA
betainc-1.0.0.dist-info/WHEEL
betainc-1.0.0.dist-info/RECORD
