Metadata-Version: 2.1
Name: betainc
Version: 1.0.0
Summary: 
Author: catethos
Author-email: cloverethos@gmail.com
Requires-Python: >=3.8,<3.11
Classifier: Programming Language :: Python :: 3
Classifier: Programming Language :: Python :: 3.8
Classifier: Programming Language :: Python :: 3.9
Classifier: Programming Language :: Python :: 3.10
Requires-Dist: Cython (>=0.29.27,<0.30.0)
Requires-Dist: numpy (>=1.22.1,<2.0.0)
